{"Macro":[{"Data":{"UnitName":"Speedwagon","CFrame":"42.3858642578125, -126.85931396484375, 18.81536865234375","Index":1},"Time":3.96,"Event":"Summon"},{"Data":{"Index":1},"Time":11.25,"Event":"Upgrade"},{"Data":{"Index":1},"Time":24.47,"Event":"Upgrade"},{"Data":{"Index":1},"Time":25.97,"Event":"Upgrade"},{"Data":{"UnitName":"Metal Cooler","CFrame":"-4.6351318359375, -121.5731201171875, 22.31793212890625","Index":2},"Time":38,"Event":"Summon"},{"Data":{"UnitName":"Metal Cooler","CFrame":"46.2896728515625, -121.57308959960938, 0.31280517578125","Index":3},"Time":40.93,"Event":"Summon"},{"Data":{"UnitName":"Metal Cooler","CFrame":"46.3197021484375, -121.57308959960938, 4.07696533203125","Index":4},"Time":41.58,"Event":"Summon"},{"Data":{"UnitName":"Metal Cooler","CFrame":"31.8814697265625, -121.57308959960938, 16.55743408203125","Index":5},"Time":43.26,"Event":"Summon"},{"Data":{"UnitName":"Metal Cooler","CFrame":"31.5582275390625, -121.57308959960938, 13.60430908203125","Index":6},"Time":48.71,"Event":"Summon"},{"Data":{"Index":1},"Time":50.05,"Event":"Upgrade"},{"Data":{"Index":1},"Time":51.18,"Event":"Upgrade"},{"Data":{"Index":1},"Time":52.32,"Event":"Upgrade"},{"Data":{"Index":1},"Time":53.29,"Event":"Upgrade"},{"Data":{"Index":1},"Time":57.2,"Event":"Upgrade"},{"Data":{"Index":1},"Time":63.9,"Event":"Upgrade"},{"Data":{"Index":1},"Time":64.77,"Event":"Upgrade"},{"Data":{"Index":1},"Time":77.11,"Event":"Upgrade"},{"Data":{"Index":1},"Time":78.27,"Event":"Upgrade"},{"Data":{"Index":1},"Time":90.3,"Event":"Upgrade"},{"Data":{"Index":1},"Time":91.18,"Event":"Upgrade"},{"Data":{"UnitName":"Super 17","CFrame":"11.5255126953125, -126.7608642578125, -13.40850830078125","Index":7},"Time":100.1,"Event":"Summon"},{"Data":{"Index":7},"Time":101.67,"Event":"Upgrade"},{"Data":{"Index":7},"Time":101.88,"Event":"Upgrade"},{"Data":{"Index":7},"Time":103,"Event":"ChangePriority"},{"Data":{"UnitName":"Super 17","CFrame":"48.1148681640625, -126.7608642578125, -6.91583251953125","Index":8},"Time":105.55,"Event":"Summon"},{"Data":{"Index":8},"Time":106.88,"Event":"Upgrade"},{"Data":{"Index":8},"Time":107.22,"Event":"Upgrade"},{"Data":{"Index":8},"Time":108.09,"Event":"ChangePriority"},{"Data":{"UnitName":"Super 17","CFrame":"-15.5457763671875, -126.7608642578125, 44.28485107421875","Index":9},"Time":111.04,"Event":"Summon"},{"Data":{"Index":9},"Time":112.22,"Event":"Upgrade"},{"Data":{"Index":9},"Time":112.65,"Event":"Upgrade"},{"Data":{"Index":9},"Time":113.38,"Event":"ChangePriority"},{"Data":{"UnitName":"Hoshino","CFrame":"1.02099609375, -126.74005126953125, 9.77117919921875","Index":10},"Time":118.89,"Event":"Summon"},{"Data":{"Index":10},"Time":120.17,"Event":"Upgrade"},{"Data":{"Index":10},"Time":123.37,"Event":"Upgrade"},{"Data":{"Index":1},"Time":129.57,"Event":"Upgrade"},{"Data":{"Index":1},"Time":130.59,"Event":"Upgrade"},{"Data":{"Index":1},"Time":142.77,"Event":"Upgrade"},{"Data":{"Index":1},"Time":143.54,"Event":"Upgrade"},{"Data":{"Index":1},"Time":155.94,"Event":"Upgrade"},{"Data":{"Index":1},"Time":157.07,"Event":"Upgrade"},{"Data":{"Index":1},"Time":169.07,"Event":"Upgrade"},{"Data":{"Index":1},"Time":169.97,"Event":"Upgrade"},{"Data":{"Index":1},"Time":182.2,"Event":"Upgrade"}],"Config":{"Macro Type":"Paid","Select Macro Must Wait Event":["Sell","ChangePriority","UseSpecialMove","UseMultipleAbilities","AutoToggle","VoteWaveConfirm","VoteGameMode","SpeedChange","AutoSkipWaves_CHANGE"],"Timer Type":"First Enemy","Unit":{"Hoshino":{"Orb":"Cost Orb","Level":175},"Super 17":{"Orb":"Fire Rage Orb","Level":175},"Metal Cooler":{"Orb":"Super BlueEye Orb","Level":175},"Speedwagon":{"Orb":"Universal Reduction Orb","Level":175},"RoyxLeader_Tanjiro 7":{"Orb":"N/A","Level":"N/A","Leader":true}}}}