{"Macro":[{"Data":{"UnitName":"Super 17","CFrame":"11.11773681640625, -87.2008056640625, 0.8785400390625","Index":1},"Time":1.5,"Event":"Summon"},{"Data":{"UnitName":"Katana_Man","CFrame":"2.15118408203125, -87.2008056640625, 4.7958526611328125","Index":2},"Time":19.32,"Event":"Summon"},{"Data":{"Index":2},"Time":21.35,"Event":"ChangePriority"},{"Data":{"UnitName":"Speedwagon","CFrame":"-25.744140625, -87.29925537109375, 5.7589874267578125","Index":3},"Time":23.94,"Event":"Summon"},{"Data":{"Index":3},"Time":26.14,"Event":"Upgrade"},{"Data":{"Index":3},"Time":31.27,"Event":"Upgrade"},{"Data":{"UnitName":"Super 17","CFrame":"-130.224609375, -87.2008056640625, 3.71148681640625","Index":4},"Time":32.91,"Event":"Summon"},{"Data":{"Index":3},"Time":33.79,"Event":"Upgrade"},{"Data":{"Index":3},"Time":34.74,"Event":"Upgrade"},{"Data":{"Index":3},"Time":35.55,"Event":"Upgrade"},{"Data":{"Index":3},"Time":41.48,"Event":"Upgrade"},{"Data":{"Index":3},"Time":45.4,"Event":"Upgrade"},{"Data":{"Index":3},"Time":46.66,"Event":"Upgrade"},{"Data":{"Index":1},"Time":55.93,"Event":"Upgrade"},{"Data":{"Index":1},"Time":58.63,"Event":"Upgrade"},{"Data":{"Index":4},"Time":65.19,"Event":"Upgrade"},{"Data":{"Index":4},"Time":65.56,"Event":"Upgrade"},{"Data":{"Index":1},"Time":76.12,"Event":"ChangePriority"},{"Data":{"Index":3},"Time":79.91,"Event":"Upgrade"},{"Data":{"Index":3},"Time":80.93,"Event":"Upgrade"},{"Data":{"Index":3},"Time":81.94,"Event":"Upgrade"},{"Data":{"Index":2},"Time":82.16,"Event":"Upgrade"},{"Data":{"Index":3},"Time":84.98,"Event":"Upgrade"},{"Data":{"Index":3},"Time":85.94,"Event":"Upgrade"},{"Data":{"Index":3},"Time":98.12,"Event":"Upgrade"},{"Data":{"Index":3},"Time":98.9,"Event":"Upgrade"},{"Data":{"UnitName":"Hoshino","CFrame":"15.808837890625, -87.17999267578125, -12.679443359375","Index":5},"Time":101.13,"Event":"Summon"},{"Data":{"Index":5},"Time":102.66,"Event":"Upgrade"},{"Data":{"Index":5},"Time":105.53,"Event":"Upgrade"},{"Data":{"Index":5},"Time":109.97,"Event":"Upgrade"},{"Data":{"Index":5},"Time":110.86,"Event":"Upgrade"},{"Data":{"Index":3},"Time":111.25,"Event":"Upgrade"},{"Data":{"Index":5},"Time":112.06,"Event":"Upgrade"},{"Data":{"Index":5},"Time":112.4,"Event":"Upgrade"},{"Data":{"UnitName":"Super 17","CFrame":"23.78570556640625, -87.2008056640625, -0.465545654296875","Index":6},"Time":118.96,"Event":"Summon"},{"Data":{"Index":6},"Time":120.54,"Event":"Upgrade"},{"Data":{"Index":6},"Time":120.83,"Event":"Upgrade"},{"Data":{"Index":3},"Time":124.49,"Event":"Upgrade"},{"Data":{"Index":4},"Time":131.07,"Event":"Upgrade"},{"Data":{"Index":3},"Time":137.41,"Event":"Upgrade"},{"Data":{"Index":5},"Time":147.25,"Event":"Upgrade"},{"Data":{"Index":1},"Time":150.6,"Event":"Upgrade"},{"Data":{"Index":3},"Time":150.81,"Event":"Upgrade"},{"Data":{"Index":6},"Time":152.21,"Event":"Upgrade"},{"Data":{"UnitName":"Katana_Man","CFrame":"32.852783203125, -87.2008056640625, -12.965286254882812","Index":7},"Time":160.75,"Event":"Summon"},{"Data":{"Index":7},"Time":162.23,"Event":"Upgrade"},{"Data":{"Index":7},"Time":162.63,"Event":"Upgrade"},{"Data":{"Index":7},"Time":163.06,"Event":"Upgrade"},{"Data":{"Index":7},"Time":163.46,"Event":"Upgrade"},{"Data":{"Index":7},"Time":163.84,"Event":"Upgrade"},{"Data":{"Index":3},"Time":164.92,"Event":"Upgrade"},{"Data":{"UnitName":"Super 17","CFrame":"35.71783447265625, -87.100830078125, -14.726409912109375","Index":8},"Time":168.28,"Event":"Summon"},{"Data":{"Index":8},"Time":171.06,"Event":"Upgrade"},{"Data":{"Index":8},"Time":171.38,"Event":"Upgrade"},{"Data":{"Index":8},"Time":171.85,"Event":"Upgrade"},{"Data":{"UnitName":"Super 17","CFrame":"24.23101806640625, -87.2008056640625, -24.1328125","Index":9},"Time":173.71,"Event":"Summon"},{"Data":{"Index":9},"Time":175.44,"Event":"Upgrade"},{"Data":{"Index":9},"Time":175.75,"Event":"Upgrade"},{"Data":{"Index":9},"Time":176.22,"Event":"Upgrade"},{"Data":{"Index":3},"Time":176.8,"Event":"Upgrade"},{"Data":{"UnitName":"Katana_Man","CFrame":"19.02911376953125, -87.2008056640625, -26.33831787109375","Index":10},"Time":177.71,"Event":"Summon"},{"Data":{"Index":3},"Time":178.29,"Event":"Upgrade"},{"Data":{"Index":10},"Time":179.19,"Event":"Upgrade"},{"Data":{"Index":10},"Time":179.47,"Event":"Upgrade"},{"Data":{"Index":10},"Time":179.77,"Event":"Upgrade"},{"Data":{"UnitName":"Super 17","CFrame":"25.06597900390625, -87.2008056640625, -30.808502197265625","Index":11},"Time":202.63,"Event":"Summon"},{"Data":{"Index":11},"Time":203.8,"Event":"Upgrade"},{"Data":{"Index":11},"Time":204.21,"Event":"Upgrade"}],"Config":{"Macro Type":"Paid","Select Macro Must Wait Event":["Sell","ChangePriority","UseSpecialMove","UseMultipleAbilities","AutoToggle","VoteWaveConfirm","VoteGameMode","SpeedChange","AutoSkipWaves_CHANGE"],"Timer Type":"First Enemy","Unit":{"Katana_Man":{"Orb":"Prey Eye Orb","Level":155},"Hoshino":{"Orb":"Cost Orb","Level":175},"Speedwagon":{"Orb":"Universal Reduction Orb","Level":175},"Super 17":{"Orb":"Super BlueEye Orb","Level":175},"RoyxLeader_Tanjiro 7":{"Orb":"N/A","Level":"N/A","Leader":true}}}}